skgaze/EMDAT/AOI.py
skgaze/EMDAT/BasicParticipant.py
skgaze/EMDAT/Participant.py
skgaze/EMDAT/Recording.py
skgaze/EMDAT/Scene.py
skgaze/EMDAT/Segment.py
skgaze/EMDAT/ValidityProcessing.py
skgaze/EMDAT/__init__.py
skgaze/EMDAT/data_structures.py
skgaze/EMDAT/geometry.py
skgaze/EMDAT/params.py
skgaze/EMDAT/testBasic.py
skgaze/EMDAT/utils.py
skgaze/RQA/RQA_funcs.py
skgaze/RQA/CustomPythonModules/DynamicalSystemsModule.py
skgaze/RQA/CustomPythonModules/SpatioTemporalEyeTrackingModule.py
skgaze/RQA/CustomPythonModules/__init__.py
skgaze/common_scanpath/Dotplots.py
skgaze/common_scanpath/STA.py
skgaze/common_scanpath/__init__.py
skgaze/common_scanpath/eMine.py
skgaze/core/Aoi.py
skgaze/core/Dataset.py
skgaze/core/EMDAT.py
skgaze/core/Participant.py
skgaze/core/RQA.py
skgaze/core/__init__.py
skgaze/pattern_search/SPAM.py
skgaze/similarity_algorithms/levenshtein_distance.py
skgaze/similarity_algorithms/longest_common_subsequence.py
skgaze/similarity_algorithms/longest_common_substring.py
skgaze/similarity_algorithms/similarity.py
scikit_gaze-0.0.9.dist-info/LICENSE.txt
scikit_gaze-0.0.9.dist-info/METADATA
scikit_gaze-0.0.9.dist-info/WHEEL
scikit_gaze-0.0.9.dist-info/top_level.txt
scikit_gaze-0.0.9.dist-info/RECORD
