Metadata-Version: 2.1
Name: scikit-gaze
Version: 0.0.9
Summary: Library for scanpath comparison
Home-page: https://github.com/zuhi6/scikit-gaze/
Author: Zajic Michal
Author-email: zajicmichal6@gmail.com
License: UNKNOWN
Platform: UNKNOWN
Classifier: Programming Language :: Python :: 3
Classifier: License :: OSI Approved :: BSD License
Classifier: Operating System :: OS Independent
